plutoniium/__init__.py
plutoniium/client.py
plutoniium-0.1.0.dist-info/licenses/LICENSE
plutoniium-0.1.0.dist-info/METADATA
plutoniium-0.1.0.dist-info/WHEEL
plutoniium-0.1.0.dist-info/top_level.txt
plutoniium-0.1.0.dist-info/RECORD
