Metadata-Version: 2.4
Name: plutoniium
Version: 0.1.0
Summary: Plutoniium AI SDK - Python API Client
Author-email: Plutoniium <support@plutoniium.com>
License: MIT
Project-URL: Homepage, https://plutoniium.com
Project-URL: Documentation, https://www.plutoniium.com/developer-docs
Requires-Python: >=3.8
License-File: LICENSE
Requires-Dist: requests>=2.25.0
Dynamic: license-file
